{
  "forge_marker": 1,
  "defaults": {
    "transform": "forge:default-block",
    "model": "half_slab",
    "textures": {
      "top": "contentcreator:blocks/rich_goldbasaltslab",
      "bottom": "contentcreator:blocks/rich_goldbasaltslab",
      "side": "contentcreator:blocks/rich_goldbasaltslab"
    }
  },
  "variants": {
    "half": {
      "bottom": {},
      "top": {
        "model": "upper_slab"
      }
    },
    "variant": {
      "normal": {}
    },
    "inventory": [
      {}
    ]
  }
}