{
    "parent": "block/block",
    "textures": {
        "plank": "blocks/planks_oak",
        "log_top": "blocks/log_oak_top",
        "top": "cosmeticwood:minecraft/blocks/crafting_table_top",
        "front": "cosmeticwood:minecraft/blocks/crafting_table_front",
        "side": "cosmeticwood:minecraft/blocks/crafting_table_side",
        "front_tools": "cosmeticwood:minecraft/blocks/crafting_table_front_tools",
        "side_tools": "cosmeticwood:minecraft/blocks/crafting_table_side_tools",
        "particle": "#plank"
    },
	"elements": [
        {   "from": [ 0, 0, 0 ],
            "to": [ 16, 16, 16 ],
            "faces": {
                "down":  { "uv": [ 0, 0, 16, 16 ], "texture": "#plank", "cullface": "down" },
                "up":    { "uv": [ 0, 0, 16, 16 ], "texture": "#log_top", "cullface": "up" },
                "north": { "uv": [ 0, 0, 16, 16 ], "texture": "#plank",   "cullface": "north" },
                "south": { "uv": [ 0, 0, 16, 16 ], "texture": "#plank",   "cullface": "south" },
                "west":  { "uv": [ 0, 0, 16, 16 ], "texture": "#plank",   "cullface": "west" },
                "east":  { "uv": [ 0, 0, 16, 16 ], "texture": "#plank",   "cullface": "east" }
            }
        },
        {   "from": [ 0, 0, 0 ],
            "to": [ 16, 16, 16 ],
            "faces": {
                "up":    { "uv": [ 0, 0, 16, 16 ], "texture": "#top",    "cullface": "up", "tintindex": 0},
                "north": { "uv": [ 0, 0, 16, 16 ], "texture": "#front",   "cullface": "north", "tintindex": 0 },
                "south": { "uv": [ 0, 0, 16, 16 ], "texture": "#side",   "cullface": "south", "tintindex": 0 },
                "west":  { "uv": [ 0, 0, 16, 16 ], "texture": "#side",   "cullface": "west", "tintindex": 0 },
                "east":  { "uv": [ 0, 0, 16, 16 ], "texture": "#side",   "cullface": "east", "tintindex": 0 }
            }
        },
		{   "from": [ 0, 0, 0 ],
            "to": [ 16, 16, 16 ],
            "faces": {
                "north": { "uv": [ 0, 0, 16, 16 ], "texture": "#front_tools",   "cullface": "north" },
                "south": { "uv": [ 0, 0, 16, 16 ], "texture": "#side_tools",   "cullface": "south" },
                "west":  { "uv": [ 0, 0, 16, 16 ], "texture": "#side_tools",   "cullface": "west" },
                "east":  { "uv": [ 0, 0, 16, 16 ], "texture": "#side_tools",   "cullface": "east" }
            }
        }
    ]
}
